{
  "$schema": "../node_modules/@tauri-apps/cli/schema.json",
  "build": {
    "beforeBuildCommand": "node ./scripts/clean-tauri-target.mjs && yarn build",
    "beforeDevCommand": "node ./scripts/clean-tauri-target.mjs && yarn dev",
    "frontendDist": "../dist",
    "devUrl": "http://localhost:3000"
  },
  "bundle": {
    "active": true,
    "category": "DeveloperTool",
    "copyright": "",
    "targets": "all",
    "externalBin": [],
    "icon": [
      "icons/32x32.png",
      "icons/128x128.png",
      "icons/128x128@2x.png",
      "icons/icon.icns",
      "icons/icon.ico"
    ],
    "windows": {
      "certificateThumbprint": null,
      "digestAlgorithm": "sha256",
      "timestampUrl": ""
    },
    "longDescription": "",
    "macOS": {
      "entitlements": null,
      "exceptionDomain": "",
      "frameworks": [],
      "providerShortName": null,
      "signingIdentity": null
    },
    "resources": [],
    "shortDescription": "",
    "linux": {
      "deb": {
        "depends": []
      }
    }
  },
  "productName": "samaura",
  "mainBinaryName": "samaura",
  "version": "1.0.17",
  "identifier": "com.samura.client",
  "plugins": {},
  "app": {
    "windows": [
      {
        "fullscreen": false,
        "height": 600,
        "resizable": true,
        "title": "samaura",
        "width": 800,
        "useHttpsScheme": true
      }
    ],
    "security": {
      "csp": null
    }
  }
}
